asgi_cable/__init__.py
asgi_cable/contrib/__init__.py
asgi_cable/contrib/django/__init__.py
asgi_cable/static/wire/socket.js
asgi_cable/websockets.py
asgi_cable-0.1.0.dist-info/WHEEL
asgi_cable-0.1.0.dist-info/METADATA
asgi_cable-0.1.0.dist-info/RECORD
