Metadata-Version: 2.1
Name: asgi-cable
Version: 0.1.0
Summary: A framework for the real-time ASGI apps.
License: MIT
Author: Alex Oleshkevich
Author-email: alex.oleshkevich@gmail.com
Requires-Python: >=3.7,<4.0
Classifier: License :: OSI Approved :: MIT License
Classifier: Programming Language :: Python :: 3
Classifier: Programming Language :: Python :: 3.7
Classifier: Programming Language :: Python :: 3.8
